emulator/__init__.py
emulator/emulator.py
emulator/channels/__init__.py
emulator/channels/channel.py
emulator/channels/dc_channel.py
emulator/channels/rf_channel.py
emulator/config/__init__.py
emulator/config/channel_config.py
emulator/config/hardware_config.py
emulator/config/qubit_config.py
emulator/data/__init__.py
emulator/data/dc_sim_data.py
emulator/data/result.py
emulator/data/rf_sim_data.py
emulator/data/sim_data.py
emulator/hardware/__init__.py
emulator/hardware/adc.py
emulator/hardware/core.py
emulator/hardware/dac.py
emulator/hardware/distributed_processor.py
emulator/hardware/function_processor.py
emulator/hardware/qubit.py
emulator/hardware/resonator.py
emulator/parsers/__init__.py
emulator/parsers/buffer_parser.py
emulator/parsers/cfg_generator.py
emulator/parsers/command_parser.py
lbl_qubic_emulator-0.3.dist-info/licenses/LICENSE
lbl_qubic_emulator-0.3.dist-info/METADATA
lbl_qubic_emulator-0.3.dist-info/WHEEL
lbl_qubic_emulator-0.3.dist-info/top_level.txt
lbl_qubic_emulator-0.3.dist-info/RECORD
