Metadata-Version: 2.4
Name: lbl-qubic-emulator
Version: 0.3
License-File: LICENSE
Requires-Dist: numpy
Requires-Dist: matplotlib
Requires-Dist: pyvcd
Requires-Dist: pyyaml
Requires-Dist: scipy
Requires-Dist: qutip
Dynamic: license-file
Dynamic: requires-dist
